pandas_multiprocessing/__init__.py
pandas_multiprocessing/mp_generic.py
pandas_multiprocessing-0.2.1.dist-info/DESCRIPTION.rst
pandas_multiprocessing-0.2.1.dist-info/METADATA
pandas_multiprocessing-0.2.1.dist-info/RECORD
pandas_multiprocessing-0.2.1.dist-info/WHEEL
pandas_multiprocessing-0.2.1.dist-info/metadata.json
pandas_multiprocessing-0.2.1.dist-info/top_level.txt
