Metadata-Version: 2.0
Name: pandas-multiprocessing
Version: 0.2.1
Summary: Pandas Multiprocessing Support
Home-page: https://github.com/amro-pydev/pandas_multiprocessing.git
Author: Amro Tork
Author-email: amrsfmt@yahoo.com
License: BSD
Platform: UNKNOWN
Classifier: Development Status :: 3 - Alpha
Classifier: Intended Audience :: Developers
Classifier: Intended Audience :: Education
Classifier: Intended Audience :: Science/Research
Classifier: License :: OSI Approved :: BSD License
Classifier: Topic :: Scientific/Engineering
Classifier: Programming Language :: Python :: 2
Classifier: Programming Language :: Python :: 2.7
Classifier: Programming Language :: Python :: 3
Classifier: Programming Language :: Python :: 3.4
Classifier: Programming Language :: Python :: 3.5
Requires-Dist: numpy
Requires-Dist: pandas (>=0.17.1)
